{
    "Nombre Candidato": "ALFONSO JAVIER FLORES PADILLA",
    "Cargo": "Juezas/es de Distrito",
    "Entidad": "BAJA CALIFORNIA",
    "Sexo": "HOMBRE",
    "Telefono": "5551395889",
    "Correo Electronico": "juezalfonsoflores74@gmail.com",
    "Numero de lista en boleta": "*No especificado*",
    "Escolaridad": "Maestría",
    "Estatus Escolaridad": "Cédula profesional",
    "Tags Educación": [
        "Agro",
        "Derecho Comercial Internacional",
        "Derecho Procesal Agrario",
        "Derechos Humanos",
        "Especialización Judicial",
        "Justicia para Adolescentes",
        "Licenciatura en Contabilidad.",
        "Licenciatura en Derecho",
        "Maestría en Derecho Fiscal",
        "Poder Judicial de la Federación",
        "UNAM"
    ],
    "Tags Propósito": [
        "Atención ciudadana",
        "Eficacia",
        "Justicia accesible",
        "Justicia gratuita",
        "Justicia social",
        "Necesitados.",
        "Rapidez",
        "Servir a la sociedad",
        "Transparencia"
    ],
    "Descripción del Candidato": "Descripción del Candidato\nAlfonso Javier Flores Padilla es candidato a Juez/a de Distrito en Baja California, postulándose en la vía “En Funciones”. Cuenta con una Maestría en Derecho Fiscal y es Licenciado en Derecho por la UNAM, además de poseer una Licenciatura en Contabilidad. Su formación incluye diversos diplomados y especializaciones en áreas como Derecho Procesal Agrario, Derechos Humanos y Justicia para Adolescentes.\n\nFlores Padilla motiva su búsqueda del cargo en el deseo de lograr la justicia social y su visión se centra en una justicia abierta, transparente, accesible y rápida. Sus propuestas principales son agilizar los procesos judiciales, garantizar el acceso a la justicia gratuita y brindar atención directa y personalizada a los ciudadanos.",
    "Poder que postula": [
        "En Funciones"
    ],
    "Pagina Web": "No proporcionó",
    "Redes Sociales": [
        "https://www.facebook.com/share/155QwvPk6N/?mibextid=wwXIfr",
        "https://www.instagram.com/juezalfonsoflores?igsh=MWlyMXR3ODlsbml4Zg==",
        "https://www.tiktok.com/@juez.alfonso.flore?_t=ZT-8v4C2lM2x1K&_r=1"
    ],
    "Cursos": [
        "- DIPLOMADO EN DERECHO PROCESAL AGRARIO; VISIÓN   DEL AGRO EN EL NUEVO MILENIO, TRIBUNAL",
        "- ,DERECHOS HUMANOS",
        "- PODER JUDICIAL DE LA FEDERACIÓN",
        "- ,DERECHO COMERCIAL INTERNACIONAL,ESPECIALIZACIÓN JUDICIAL",
        "- ,ESPECIALIZACIÓN EN JUSTICIA PARA ADOLESCENTES"
    ],
    "Curriculum Vitae": "https://candidaturaspoderjudicial.ine.mx/detalleCandidato/52906/11",
    "Trayectoria Academica": "- LICENCIADO EN DERECHO POR LA UNAM, MAESTRO EN DERECHO FISCAL Y LICENCIADO EN CONTABILIDAD",
    "Motivo para buscar el Cargo Publico": "PARA LOGRAR ESA JUSTICIA SOCIAL POR LA QUE TODAS Y TODOS HEMOS LUCHADO HASTA HOY.",
    "Vision sobre la Funcion Jurisdiccional": "UNA JUSTICIA ABIERTA, TRANSPARENTE, QUE LLEGUE AL MÁS NECESITADO. LOGRAR UNA JUSTICIA ACCESIBLE A TODAS O TODOS. JUSTICIA PARA TI, AÚN SIN CONTAR CON UNA ABOGADA O ABOGADO QUE TE DEFIENDA.",
    "Vision sobre la Imparticion de Justicia": "RÁPIDA, EFICAZ Y A AL ALCANCE DE TODOS. DEMOSTRAR A LA PÓBLACION QUE LOS JUECES ESTÁN PARA SERVIR A LA SOCIEDAD.",
    "Propuestas": "- RAPIDEZ\n- JUSTICIA GRATUITA\n- ATENCION DIRECTA Y PERSONAL A LOS CIUDADANOS"
}