{
    "Nombre Candidato": "LUZ MARIA ORTEGA TLAPA",
    "Cargo": "Juezas/es de Distrito",
    "Entidad": "MEXICO",
    "Sexo": "MUJER",
    "Telefono": "No proporcionó",
    "Correo Electronico": "No proporcionó",
    "Numero de lista en boleta": "*No especificado*",
    "Escolaridad": "No proporcionó",
    "Estatus Escolaridad": "No proporcionó",
    "Tags Educación": [
        "No proporcionó"
    ],
    "Tags Propósito": [
        "ausencia",
        "falta de propuestas",
        "inexistencia",
        "inexistente.",
        "irrelevante",
        "no hay visión",
        "nulo",
        "silencio",
        "sin contenido",
        "vacío"
    ],
    "Descripción del Candidato": "Descripción del Candidato\nLUZ MARIA ORTEGA TLAPA es candidata a Juezas/es de Distrito en la entidad de MEXICO, postulándose en la categoría de En Funciones. Es de sexo femenino y no proporcionó información de contacto (teléfono, correo electrónico, página web o redes sociales).\n\nNo se cuenta con datos sobre su escolaridad, trayectoria académica, motivaciones para buscar el cargo público, ni propuestas en materia de función jurisdiccional o impartición de justicia. Su estatus en el sistema es \"Sin captura\".",
    "Poder que postula": [
        "En Funciones"
    ],
    "Pagina Web": "No proporcionó",
    "Redes Sociales": [
        "No proporcionó"
    ],
    "Cursos": [
        "- No proporcionó"
    ],
    "Curriculum Vitae": "No proporcionó",
    "Trayectoria Academica": "- No proporcionó",
    "Motivo para buscar el Cargo Publico": "No proporcionó",
    "Vision sobre la Funcion Jurisdiccional": "No proporcionó",
    "Vision sobre la Imparticion de Justicia": "No proporcionó",
    "Propuestas": "- No proporcionó\n- No proporcionó\n- No proporcionó"
}